tptool/__init__.py
tptool/__main__.py
tptool/app.py
tptool/common/__init__.py
tptool/common/architecture.py
tptool/common/arguments.py
tptool/common/filemanager.py
tptool/common/logger.py
tptool/common/ringbuffer.py
tptool/config/__init__.py
tptool/config/configs.py
tptool/config/generator.py
tptool/config/tpconfig_template.h
tptool/processing/__init__.py
tptool/processing/csv.py
tptool/processing/parser.py
tptool/processing/serial.py
tptool/processing/simulator.py
tptool/processing/worker.py
tptool/ui/Makefile
tptool/ui/__init__.py
tptool/ui/mainwindow.py
tptool/ui/popup.py
tptool/ui/touchmain.ui
tptool/ui/ui_touchmain.py
tptool-0.0.4.dist-info/METADATA
tptool-0.0.4.dist-info/WHEEL
tptool-0.0.4.dist-info/licenses/LICENSE.txt
tptool-0.0.4.dist-info/RECORD
