Metadata-Version: 2.1
Name: tptool
Version: 0.0.4
Summary: ESP32 Touchpad Debugging Tool
Project-URL: Homepage, https://esp32.com/viewtopic.php?f=22&t=29065
Project-URL: Bug Tracker, https://esp32.com/viewtopic.php?f=22&t=29065
Author-email: Bob Lee <libo@espressif.com>
License-File: LICENSE.txt
Classifier: License :: OSI Approved :: GNU Lesser General Public License v3 (LGPLv3)
Classifier: Operating System :: OS Independent
Classifier: Programming Language :: Python :: 3
Requires-Python: >=3.7
Requires-Dist: numpy
Requires-Dist: pyqtgraph
Requires-Dist: pyserial
Requires-Dist: pyside2
